requirements.txt
setup.py
pypi_simple_iter/__init__.py
pypi_simple_iter.egg-info/PKG-INFO
pypi_simple_iter.egg-info/SOURCES.txt
pypi_simple_iter.egg-info/dependency_links.txt
pypi_simple_iter.egg-info/requires.txt
pypi_simple_iter.egg-info/top_level.txt