Metadata-Version: 2.1
Name: pypi-simple-iter
Version: 2020.7.1
Summary: pypi simple https://pypi.org/simple/ iterator
Home-page: https://github.com/andrewp-as-is/pypi-simple-iter.py
License: Unlicense
Keywords: pypi simple
Platform: UNKNOWN
Classifier: License :: Public Domain
Classifier: Operating System :: OS Independent
Classifier: Programming Language :: Python :: 3
